invenio_app_ils/__init__.py
invenio_app_ils/cli.py
invenio_app_ils/config.py
invenio_app_ils/errors.py
invenio_app_ils/ext.py
invenio_app_ils/facets.py
invenio_app_ils/fetchers.py
invenio_app_ils/indexer.py
invenio_app_ils/minters.py
invenio_app_ils/permissions.py
invenio_app_ils/proxies.py
invenio_app_ils/search_permissions.py
invenio_app_ils/signals.py
invenio_app_ils/views.py
invenio_app_ils/webpack.py
invenio_app_ils/acquisition/__init__.py
invenio_app_ils/acquisition/api.py
invenio_app_ils/acquisition/config.py
invenio_app_ils/acquisition/errors.py
invenio_app_ils/acquisition/ext.py
invenio_app_ils/acquisition/indexer.py
invenio_app_ils/acquisition/proxies.py
invenio_app_ils/acquisition/search.py
invenio_app_ils/acquisition/jsonresolvers/__init__.py
invenio_app_ils/acquisition/jsonresolvers/order_order_lines.py
invenio_app_ils/acquisition/jsonresolvers/order_provider.py
invenio_app_ils/acquisition/loaders/__init__.py
invenio_app_ils/acquisition/loaders/jsonschemas/__init__.py
invenio_app_ils/acquisition/loaders/jsonschemas/order.py
invenio_app_ils/acquisition/mappings/__init__.py
invenio_app_ils/acquisition/mappings/os-v1/__init__.py
invenio_app_ils/acquisition/mappings/os-v1/acq_orders/order-v1.0.0.json
invenio_app_ils/acquisition/mappings/os-v2/__init__.py
invenio_app_ils/acquisition/mappings/os-v2/acq_orders/order-v1.0.0.json
invenio_app_ils/acquisition/mappings/v7/__init__.py
invenio_app_ils/acquisition/mappings/v7/acq_orders/order-v1.0.0.json
invenio_app_ils/acquisition/schemas/__init__.py
invenio_app_ils/acquisition/schemas/acq_orders/order-v1.0.0.json
invenio_app_ils/acquisition/stats/__init__.py
invenio_app_ils/acquisition/stats/views.py
invenio_app_ils/assets/semantic-ui/less/theme.config
invenio_app_ils/assets/semantic-ui/templates/.gitkeep
invenio_app_ils/circulation/__init__.py
invenio_app_ils/circulation/api.py
invenio_app_ils/circulation/config.py
invenio_app_ils/circulation/errors.py
invenio_app_ils/circulation/indexer.py
invenio_app_ils-7.1.0.dist-info/licenses/AUTHORS.rst
invenio_app_ils-7.1.0.dist-info/licenses/LICENSE
invenio_app_ils-7.1.0.dist-info/METADATA
invenio_app_ils-7.1.0.dist-info/WHEEL
invenio_app_ils-7.1.0.dist-info/entry_points.txt
invenio_app_ils-7.1.0.dist-info/top_level.txt
invenio_app_ils-7.1.0.dist-info/RECORD
