Metadata-Version: 2.4
Name: invenio-app-ils
Version: 7.1.0
Summary: Invenio Integrated Library System.
Home-page: https://github.com/inveniosoftware/invenio-app-ils
Author: CERN
Author-email: info@inveniosoftware.org
License: MIT
Keywords: invenio-app-ils Invenio
Platform: any
Classifier: Development Status :: 4 - Beta
Requires-Python: >=3.8
License-File: LICENSE
License-File: AUTHORS.rst
Requires-Dist: invenio-app<3.0.0,>=2.3.0
Requires-Dist: invenio-db[mysql,postgresql]<3.0.0,>=2.0.0
Requires-Dist: invenio-base<3.0.0,>=2.3.2
Requires-Dist: invenio-cache<3.0.0,>=2.1.0
Requires-Dist: invenio-celery<3.0.0,>=2.2.0
Requires-Dist: invenio-config<2.0.0,>=1.1.0
Requires-Dist: invenio-i18n<4.0.0,>=3.3.0
Requires-Dist: invenio-assets<5.0.0,>=4.2.0
Requires-Dist: invenio-formatter<4.0.0,>=3.2.0
Requires-Dist: invenio-logging[sentry]<5.0.0,>=4.1.0
Requires-Dist: invenio-mail<3.0.0,>=2.3.0
Requires-Dist: invenio-rest<3.0.0,>=2.0.5
Requires-Dist: invenio-theme<5.0.0,>=4.3.0
Requires-Dist: invenio-access<5.0.0,>=4.1.0
Requires-Dist: invenio-accounts<7.0.0,>=6.1.1
Requires-Dist: invenio-oauth2server<4.0.0,>=3.2.0
Requires-Dist: invenio-oauthclient<7.0.0,>=6.0.0
Requires-Dist: invenio-userprofiles<5.0.0,>=4.0.0
Requires-Dist: invenio-indexer<4.0.0,>=3.1.0
Requires-Dist: invenio-jsonschemas<3.0.0,>=2.1.0
Requires-Dist: invenio-oaiserver<4.0.0,>=3.6.0
Requires-Dist: invenio-pidstore<3.0.0,>=2.1.0
Requires-Dist: invenio-records-rest<4.0.0,>=3.1.0
Requires-Dist: invenio-records<4.0.0,>=3.0.2
Requires-Dist: invenio-files-rest<4.0.0,>=3.2.0
Requires-Dist: invenio-banners<6.0.0,>=5.0.0
Requires-Dist: invenio-pages<8.0.0,>=7.1.0
Requires-Dist: invenio-circulation<5.0.0,>=4.0.0
Requires-Dist: invenio-opendefinition<3.0.0,>=2.0.0a2
Requires-Dist: invenio-pidrelations<2.0.0,>=1.0.0
Requires-Dist: invenio-stats<6.0.0,>=5.1.1
Requires-Dist: Flask-Debugtoolbar<1.0.0,>=0.15.1
Requires-Dist: pycountry<25.0.0,>=22.3.5
Requires-Dist: simplejson<4.0.0,>=3.20.1
Requires-Dist: jsonschema<5.0.0,>=4.24.0
Requires-Dist: alembic<2.0.0,>=1.16.4
Requires-Dist: celery<5.4.0,>=5.3.6
Requires-Dist: billiard<5.0.0,>=4.2.1
Requires-Dist: werkzeug<4.0.0,>=3.1.3
Requires-Dist: click<9.0.0,>=8.1.8
Requires-Dist: sqlalchemy_utils>=0.41.2
Provides-Extra: tests
Requires-Dist: pytest-black>=0.3.0; extra == "tests"
Requires-Dist: mock>=2.0.0; extra == "tests"
Requires-Dist: pytest-invenio>=3.4.2; extra == "tests"
Requires-Dist: docker-services-cli>=0.6.0; extra == "tests"
Requires-Dist: pydocstyle==6.1.1; extra == "tests"
Requires-Dist: pytest-mock>=1.6.0; extra == "tests"
Requires-Dist: sphinx>=5; extra == "tests"
Requires-Dist: pluggy>=1.6.0; extra == "tests"
Provides-Extra: lorem
Requires-Dist: lorem>=0.1.1; extra == "lorem"
Provides-Extra: opensearch2
Requires-Dist: invenio-search[opensearch2]<4.0.0,>=3.1.0; extra == "opensearch2"
Provides-Extra: docs
Dynamic: license-file
